client/__init__.py
client/client.py
client/launcher.py
client/client/__init__.py
client/client/client_main_window.py
client/client/database.py
client/client/main_window_handler.py
client/client/message_handler.py
client/client/start_window.py
client/client/warning_window.py
client/common/__init__.py
client/common/descripts.py
client/common/handler.py
client/common/metaclasses.py
client/common/parser.py
client/unit_tests/__init__.py
fine_messanger_client-0.0.1.dist-info/METADATA
fine_messanger_client-0.0.1.dist-info/WHEEL
fine_messanger_client-0.0.1.dist-info/top_level.txt
fine_messanger_client-0.0.1.dist-info/RECORD
