Metadata-Version: 2.1
Name: fine-messanger-client
Version: 0.0.1
Summary: client
Author: Vyacheslav
Author-email: slavkin.131@gmail.com
License: UNKNOWN
Platform: UNKNOWN
Requires-Dist: PyQt5
Requires-Dist: sqlalchemy
Requires-Dist: pycryptodome
Requires-Dist: pycryptodomex
